pyevolutionapi/__init__.py
pyevolutionapi/auth.py
pyevolutionapi/client.py
pyevolutionapi/exceptions.py
pyevolutionapi/py.typed
pyevolutionapi/models/__init__.py
pyevolutionapi/models/base.py
pyevolutionapi/models/chat.py
pyevolutionapi/models/group.py
pyevolutionapi/models/instance.py
pyevolutionapi/models/message.py
pyevolutionapi/models/webhook.py
pyevolutionapi/resources/__init__.py
pyevolutionapi/resources/base.py
pyevolutionapi/resources/chat.py
pyevolutionapi/resources/group.py
pyevolutionapi/resources/instance.py
pyevolutionapi/resources/message.py
pyevolutionapi/resources/profile.py
pyevolutionapi/resources/webhook.py
pyevolutionapi-0.1.1.dist-info/licenses/LICENSE
pyevolutionapi-0.1.1.dist-info/METADATA
pyevolutionapi-0.1.1.dist-info/WHEEL
pyevolutionapi-0.1.1.dist-info/top_level.txt
pyevolutionapi-0.1.1.dist-info/RECORD
