Metadata-Version: 2.4
Name: pyevolutionapi
Version: 0.1.1
Summary: Python client for Evolution API - WhatsApp integration made simple
Author-email: Luiz Paulo Coutinho <coutinholps@gmail.com>
License: MIT
Project-URL: Homepage, https://github.com/lpcoutinho/pyevolutionapi
Project-URL: Documentation, https://lpcoutinho.github.io/pyevolutionapi
Project-URL: Repository, https://github.com/lpcoutinho/pyevolutionapi
Project-URL: Issues, https://github.com/lpcoutinho/pyevolutionapi/issues
Classifier: Development Status :: 3 - Alpha
Classifier: Intended Audience :: Developers
Classifier: Operating System :: OS Independent
Classifier: Programming Language :: Python :: 3
Classifier: Programming Language :: Python :: 3.8
Classifier: Programming Language :: Python :: 3.9
Classifier: Programming Language :: Python :: 3.10
Classifier: Programming Language :: Python :: 3.11
Classifier: Programming Language :: Python :: 3.12
Classifier: Topic :: Software Development :: Libraries :: Python Modules
Classifier: Topic :: Communications :: Chat
Requires-Python: >=3.8
License-File: LICENSE
Requires-Dist: httpx>=0.24.0
Requires-Dist: pydantic>=2.0.0
Requires-Dist: python-dotenv>=1.0.0
Requires-Dist: typing-extensions>=4.5.0; python_version < "3.10"
Provides-Extra: async
Requires-Dist: aiofiles>=23.0.0; extra == "async"
Provides-Extra: dev
Requires-Dist: pytest>=7.3.0; extra == "dev"
Requires-Dist: pytest-asyncio>=0.21.0; extra == "dev"
Requires-Dist: pytest-cov>=4.0.0; extra == "dev"
Requires-Dist: pytest-mock>=3.10.0; extra == "dev"
Requires-Dist: black>=23.3.0; extra == "dev"
Requires-Dist: ruff>=0.0.270; extra == "dev"
Requires-Dist: mypy>=1.3.0; extra == "dev"
Requires-Dist: pre-commit>=3.3.0; extra == "dev"
Requires-Dist: bump2version>=1.0.1; extra == "dev"
Provides-Extra: docs
Requires-Dist: mkdocs>=1.4.3; extra == "docs"
Requires-Dist: mkdocs-material>=9.1.0; extra == "docs"
Requires-Dist: mkdocstrings[python]>=0.21.0; extra == "docs"
Dynamic: license-file
